NotifyUI/NotifyElements.py
NotifyUI/__init__.py
NotifyUI-0.0.3.dist-info/LICENSE
NotifyUI-0.0.3.dist-info/METADATA
NotifyUI-0.0.3.dist-info/WHEEL
NotifyUI-0.0.3.dist-info/top_level.txt
NotifyUI-0.0.3.dist-info/RECORD
