Metadata-Version: 2.1
Name: NotifyUI
Version: 0.0.3
Summary: Python Notification library integrated with PyQt6
Home-page: https://github.com/chetan0402/NotifyUI
Author: Chetan0402
License: CC BY 4.0
Classifier: Programming Language :: Python :: 3
Requires: PyQt6
License-File: LICENSE
Requires-Dist: PyQt6
